sshpubkeys/__init__.py
sshpubkeys/exceptions.py
sshpubkeys/keys.py
sshpubkeys-3.3.0.dist-info/LICENSE.txt
sshpubkeys-3.3.0.dist-info/METADATA
sshpubkeys-3.3.0.dist-info/WHEEL
sshpubkeys-3.3.0.dist-info/top_level.txt
sshpubkeys-3.3.0.dist-info/RECORD
