Metadata-Version: 2.1
Name: sshpubkeys
Version: 3.3.0
Summary: SSH public key parser
Home-page: https://github.com/ojarva/python-sshpubkeys
Author: Olli Jarva
Author-email: olli@jarva.fi
License: BSD
Keywords: ssh pubkey public key openssh ssh-rsa ssh-dss ssh-ed25519
Platform: UNKNOWN
Classifier: Development Status :: 4 - Beta
Classifier: Intended Audience :: Developers
Classifier: Intended Audience :: System Administrators
Classifier: Topic :: Security
Classifier: License :: OSI Approved :: BSD License
Classifier: Programming Language :: Python :: 3
Classifier: Programming Language :: Python :: 3.6
Classifier: Programming Language :: Python :: 3.7
Classifier: Programming Language :: Python :: 3.8
Classifier: Programming Language :: Python :: Implementation :: PyPy
Requires-Python: >=3
Requires-Dist: cryptography (>=2.1.4)
Requires-Dist: ecdsa (>=0.13)
Provides-Extra: dev
Requires-Dist: twine ; extra == 'dev'
Requires-Dist: wheel ; extra == 'dev'
Requires-Dist: yapf ; extra == 'dev'
